ormar_postgres_extensions/__init__.py
ormar_postgres_extensions/fields/__init__.py
ormar_postgres_extensions/fields/array.py
ormar_postgres_extensions/fields/cidr.py
ormar_postgres_extensions/fields/inet.py
ormar_postgres_extensions/fields/jsonb.py
ormar_postgres_extensions/fields/macaddr.py
ormar_postgres_extensions/fields/uuid.py
ormar_postgres_extensions-2.3.0.dist-info/LICENSE
ormar_postgres_extensions-2.3.0.dist-info/METADATA
ormar_postgres_extensions-2.3.0.dist-info/WHEEL
ormar_postgres_extensions-2.3.0.dist-info/top_level.txt
ormar_postgres_extensions-2.3.0.dist-info/RECORD
