Metadata-Version: 2.1
Name: ormar-postgres-extensions
Version: 2.3.0
Summary: PostgreSQL specific extensions to the Ormar ORM
Home-page: https://github.com/tophat/ormar-postgres-extensions
Author: Top Hat Open Source
Author-email: opensource@tophat.com
License: Apache License 2.0
Classifier: Development Status :: 1 - Planning
Classifier: Intended Audience :: Developers
Classifier: Operating System :: OS Independent
Classifier: Programming Language :: Python :: 3
Classifier: Programming Language :: Python :: 3.8
Classifier: Programming Language :: Python :: 3.9
Classifier: Programming Language :: Python :: 3.10
Classifier: Topic :: Software Development :: Libraries
Requires-Python: >=3.8
Provides-Extra: dev
Provides-Extra: test
License-File: LICENSE
